<?xml version="1.0" encoding="UTF-8"?>
<objects serializationModel="Studio.02.02.00">
	<object class="AudioFile" id="{51686d63-f947-4de1-99ab-1df4680d4f69}">
		<property name="color">
			<value>Blue</value>
		</property>
		<property name="assetPath">
			<value>garage/lift.wav</value>
		</property>
		<property name="frequencyInKHz">
			<value>44.0999985</value>
		</property>
		<property name="channelCount">
			<value>2</value>
		</property>
		<property name="length">
			<value>9.241541950113378</value>
		</property>
		<relationship name="masterAssetFolder">
			<destination>{7eb4515f-1cee-4cf1-8d6f-7f217b12a188}</destination>
		</relationship>
	</object>
</objects>
